CHANGES.txt
COPYING.txt
LICENSE.txt
README.rst
THANKS.txt
TODO.txt
distribute_setup.py
requirements.txt
setup.cfg
setup.py
pytvdbapi/__init__.py
pytvdbapi/_compat.py
pytvdbapi/actor.py
pytvdbapi/api.py
pytvdbapi/backport.py
pytvdbapi/banner.py
pytvdbapi/error.py
pytvdbapi/loader.py
pytvdbapi/mirror.py
pytvdbapi/urls.py
pytvdbapi/utils.py
pytvdbapi/xmlhelpers.py
pytvdbapi.egg-info/PKG-INFO
pytvdbapi.egg-info/SOURCES.txt
pytvdbapi.egg-info/dependency_links.txt
pytvdbapi.egg-info/requires.txt
pytvdbapi.egg-info/top_level.txt
pytvdbapi/tests/__init__.py
pytvdbapi/tests/basetest.py
pytvdbapi/tests/test_actors.py
pytvdbapi/tests/test_api.py
pytvdbapi/tests/test_banner.py
pytvdbapi/tests/test_compat.py
pytvdbapi/tests/test_docs.py
pytvdbapi/tests/test_languages.py
pytvdbapi/tests/test_loader.py
pytvdbapi/tests/test_mirror.py
pytvdbapi/tests/test_utils.py
pytvdbapi/tests/utils.py
pytvdbapi/tests/data/mirrors.xml