Metadata-Version: 1.1
Name: pytvdbapi
Version: 0.5.0
Summary: A clean, resource friendly and easy to use API for thetvdb.com
Home-page: https://github.com/fuzzycode/pytvdbapi
Author: Bjoern Larsson
Author-email: develop@bjornlarsson.net
License: LGPLv3
Keywords: TVDB thetvdb.com API tv episodes
Platform: any
Classifier: Development Status :: 4 - Beta
Classifier: Intended Audience :: Developers
Classifier: Operating System :: OS Independent
Classifier: License :: OSI Approved :: GNU Library or Lesser General Public License (LGPL)
Classifier: Programming Language :: Python
Classifier: Programming Language :: Python :: 2.6
Classifier: Programming Language :: Python :: 2.7
Classifier: Programming Language :: Python :: 3
Classifier: Programming Language :: Python :: 3.3
Classifier: Programming Language :: Python :: 3.4
Classifier: Topic :: Software Development :: Libraries :: Python Modules
Classifier: Topic :: Utilities
